Metadata-Version: 2.4
Name: morphomatics
Version: 4.1.1
Summary: Geometric morphometrics in non-Euclidean shape spaces
Home-page: https://morphomatics.github.io/
Author: Christoph von Tycowicz et al.
Author-email: vontycowicz@zib.de
License: MIT License
Keywords: Shape Analysis,Morphometrics,Geometric Statistics
Classifier: Development Status :: 4 - Beta
Classifier: Intended Audience :: Developers
Classifier: Topic :: Software Development :: Build Tools
Classifier: License :: OSI Approved :: MIT License
Classifier: Programming Language :: Python :: 3.9
Classifier: Programming Language :: Python :: 3.10
Classifier: Programming Language :: Python :: 3.11
Classifier: Programming Language :: Python :: 3.12
License-File: LICENSE
Requires-Dist: jax>=0.4.25
Requires-Dist: jaxlib>=0.4.25
Requires-Dist: jraph
Requires-Dist: flax
Requires-Dist: optax
Provides-Extra: all
Requires-Dist: pymanopt>=2.0.1; extra == "all"
Dynamic: author
Dynamic: author-email
Dynamic: classifier
Dynamic: description
Dynamic: description-content-type
Dynamic: home-page
Dynamic: keywords
Dynamic: license
Dynamic: license-file
Dynamic: provides-extra
Dynamic: requires-dist
Dynamic: summary
